{
  "weather": {
    "station": "農工中心",
    "observedAt": "07/13 (一) 11:00",
    "current": {
      "temperatureC": "31",
      "apparentTemperatureC": "36",
      "humidityPercent": "73",
      "hourlyRainMm": "0.0",
      "sunrise": "05:14",
      "sunset": "18:48"
    },
    "today": {
      "highC": 34,
      "lowC": 28,
      "rainProbabilityPercent": 60
    },
    "source": "https://www.cwa.gov.tw/Data/js/3hr/ChartData_3hr_R_AgriM.js"
  },
  "radar": {
    "observedAt": "2026/07/13 11:10",
    "caption": "無地形，臺灣鄰近區域，靜止圖",
    "imageFile": "radar.png",
    "imageUrl": null,
    "source": "https://www.cwa.gov.tw/Data/js/obs_img/Observe_radar.js"
  },
  "water": {
    "found": false,
    "station": "新街橋",
    "liveUrl": "https://winfo.tycg.gov.tw/tysafep/Default.aspx",
    "note": "來源頁暫無「新街橋」水位資料。"
  },
  "generatedAt": "2026-07-13T03:27:14.974Z",
  "generatedAtTaipei": "2026/07/13 11:27"
}